af3jobs/__init__.py
af3jobs/components.py
af3jobs/server_jobs.py
af3jobs/standalone_jobs.py
af3jobs/utils.py
af3jobs-0.3.0.dist-info/METADATA
af3jobs-0.3.0.dist-info/WHEEL
af3jobs-0.3.0.dist-info/licenses/LICENSE
af3jobs-0.3.0.dist-info/RECORD
