Metadata-Version: 2.4
Name: af3jobs
Version: 0.3.0
Summary: Module for defining molecular components, modifications, and job configurations for AlphaFold 3
Project-URL: Homepage, https://github.com/ugSUBMARINE/af3jobs
Project-URL: Source, https://github.com/ugSUBMARINE/af3jobs
Project-URL: Tracker, https://github.com/ugSUBMARINE/af3jobs/issues
Author-email: Karl Gruber <gammaturn@gmail.com>, Gregor Wirnsberger <gregor.wirnsberger@uni-graz.at>
License: MIT
License-File: LICENSE
Keywords: AlphaFold,bioinformatics,molecular biology,protein modeling
Classifier: License :: OSI Approved :: MIT License
Classifier: Operating System :: OS Independent
Classifier: Programming Language :: Python :: 3
Classifier: Programming Language :: Python :: 3.11
Classifier: Programming Language :: Python :: 3.12
Classifier: Programming Language :: Python :: 3.13
Classifier: Programming Language :: Python :: 3.14
Requires-Python: >=3.11
